language_detection/__init__.py
language_detection/example.py
language_detection/frontend/build/asset-manifest.json
language_detection/frontend/build/bootstrap.min.css
language_detection/frontend/build/bootstrap.min.css.map
language_detection/frontend/build/index.html
language_detection/frontend/build/static/js/main.fa4f48d9.js
language_detection/frontend/build/static/js/main.fa4f48d9.js.LICENSE.txt
language_detection/frontend/build/static/js/main.fa4f48d9.js.map
streamlit_browser_language-0.0.4.dist-info/LICENSE
streamlit_browser_language-0.0.4.dist-info/METADATA
streamlit_browser_language-0.0.4.dist-info/WHEEL
streamlit_browser_language-0.0.4.dist-info/top_level.txt
streamlit_browser_language-0.0.4.dist-info/RECORD
